corelogic/__init__.py
corelogic/authentication.py
corelogic/exceptions.py
corelogic/census/__init__.py
corelogic/census/census.py
corelogic/property/__init__.py
corelogic/property/details.py
corelogic/property/search.py
corelogic/property/suggest.py
corelogic/property/valuations.py
corelogic_pyclient-0.1.3.dist-info/LICENSE
corelogic_pyclient-0.1.3.dist-info/METADATA
corelogic_pyclient-0.1.3.dist-info/WHEEL
corelogic_pyclient-0.1.3.dist-info/top_level.txt
corelogic_pyclient-0.1.3.dist-info/zip-safe
corelogic_pyclient-0.1.3.dist-info/RECORD
