Metadata-Version: 2.1
Name: corelogic-pyclient
Version: 0.1.3
Summary: CoreLogic API Wrapper for interacting with CoreLogic (Property Data Reports & Analytics)
Home-page: https://github.com/danielfarahani/corelogic_pyclient
Author: Daniel Farahani
Author-email: danfarahani@gmail.com
License: MIT
Keywords: corelogic proptech property
Platform: UNKNOWN
Classifier: Development Status :: 3 - Alpha
Classifier: License :: OSI Approved :: MIT License
Classifier: Programming Language :: Python :: 3.6
Requires-Dist: requests
